colaquant/__init__.py
colaquant/asset_analysis.py
colaquant/colafactor.py
colaquant/colafactor_object.py
colaquant/data_processing.py
colaquant/information_analysis.py
colaquant/position_analysis.py
colaquant/returns_analysis.py
colaquant/utils.py
colaquant-0.0.9.dist-info/METADATA
colaquant-0.0.9.dist-info/WHEEL
colaquant-0.0.9.dist-info/top_level.txt
colaquant-0.0.9.dist-info/RECORD
